{"type":"document","uuid":"d0526670-3536-4633-b37f-c6d8be494b4f","name":"osszegzes","struktogram":{"type":"struktogram","name":"main","helper":false,"parameters":[{"name":"m","type":"Int"},{"name":"n","type":"Int"}],"variables":[{"name":"s","type":"Int"},{"name":"i","type":"Int"}],"sequence":{"type":"sequence","commands":[{"type":"command","code":"s := 0"},{"type":"loop","condition":"i := m..n","test_after":false,"range":true,"sequence":{"type":"sequence","commands":[{"type":"command","code":"s := s + f(i)"}]}},{"type":"command","code":"return s"}]}},"helpers":[{"type":"struktogram","name":"f","helper":true,"parameters":[{"name":"i","type":"Int"}],"variables":[],"sequence":{"type":"sequence","commands":[{"type":"command","code":"return i"}]}}]}